commonsdownloader/__init__.py
commonsdownloader/commonsdownloader.py
commonsdownloader/thumbnaildownload.py
CommonsDownloader-0.5.3.dist-info/DESCRIPTION.rst
CommonsDownloader-0.5.3.dist-info/metadata.json
CommonsDownloader-0.5.3.dist-info/entry_points.txt
CommonsDownloader-0.5.3.dist-info/METADATA
CommonsDownloader-0.5.3.dist-info/WHEEL
CommonsDownloader-0.5.3.dist-info/RECORD
CommonsDownloader-0.5.3.dist-info/top_level.txt
