Metadata-Version: 2.0
Name: CommonsDownloader
Version: 0.5.3
Summary: Download thumbnails from Wikimedia Commons
Home-page: http://github.com/Commonists/CommonsDownloader
Author: Jean-Frédéric
Author-email: JeanFred@github
License: MIT
Platform: UNKNOWN
Classifier: Development Status :: 4 - Beta
Classifier: Environment :: Console
Classifier: Intended Audience :: Developers
Classifier: License :: OSI Approved :: MIT License
Classifier: Operating System :: OS Independent
Classifier: Programming Language :: Python
Classifier: Topic :: Utilities
Requires-Dist: argparse
Requires-Dist: mwclient
Requires-Dist: six
